python_color_getter/__init__.py
python_color_getter/pythonColorGetter.py
python_color_getter-0.0.1.dist-info/LICENSE
python_color_getter-0.0.1.dist-info/METADATA
python_color_getter-0.0.1.dist-info/WHEEL
python_color_getter-0.0.1.dist-info/top_level.txt
python_color_getter-0.0.1.dist-info/RECORD
