Metadata-Version: 2.1
Name: python-color-getter
Version: 0.0.1
Summary: Python color getter (including method to get random color or complementary color)
Home-page: https://github.com/yjg30737/python-color-getter.git
Author: Jung Gyu Yoon
Author-email: yjg30737@gmail.com
License: MIT
Platform: UNKNOWN
License-File: LICENSE
